README.md
setup.py
alpynet/__init__.py
alpynet/adt.py
alpynet/apn.py
alpynet/exceptions.py
alpynet.egg-info/PKG-INFO
alpynet.egg-info/SOURCES.txt
alpynet.egg-info/dependency_links.txt
alpynet.egg-info/requires.txt
alpynet.egg-info/top_level.txt
alpynet/adts/__init__.py
alpynet/adts/boolean.py
alpynet/adts/map.py
alpynet/adts/natural.py
alpynet/adts/string.py