Metadata-Version: 1.0
Name: alpynet
Version: 1.0
Summary: Algebraic Petri Nets in Python3
Home-page: https://github.com/coetaur0/alpynet
Author: Aurelien Coet
Author-email: aurelien.coet19@gmail.com
License: Apache 2
Platform: UNKNOWN
